[
    {
      "CODIGOCAUSA": 1100,
      "DESCRIPCIONCAUSA": "DAÑO MAL GENERADO",
      "CODIGOTIPODAÑO": 187594,
      "DESCRIPCIONTIPODAÑO": "BOLETA MAL GENERADA",
      "CODIGOUBICACIONDAÑO": 999,
      "DESCRIPCIONUBICACIONDAÑO": "INFUNDADO"
    },
    {
      "CODIGOCAUSA": 9416,
      "DESCRIPCIONCAUSA": "Cliente no Localizado",
      "CODIGOTIPODAÑO": 187620,
      "DESCRIPCIONTIPODAÑO": "NO SE LOCALIZA CLIENTE (3 VISITA O 2 CITAS)",
      "CODIGOUBICACIONDAÑO": 133,
      "DESCRIPCIONUBICACIONDAÑO": "CLIENTE"
    },
    {
      "CODIGOCAUSA": 9136,
      "DESCRIPCIONCAUSA": "CASA CERRADA",
      "CODIGOTIPODAÑO": 187620,
      "DESCRIPCIONTIPODAÑO": "NO SE LOCALIZA CLIENTE (3 VISITA O 2 CITAS)",
      "CODIGOUBICACIONDAÑO": 133,
      "DESCRIPCIONUBICACIONDAÑO": "CLIENTE"
    },
    {
      "CODIGOCAUSA": 5526,
      "DESCRIPCIONCAUSA": "Problemas en TV del Cliente",
      "CODIGOTIPODAÑO": 187576,
      "DESCRIPCIONTIPODAÑO": "TELEVISOR DEL CLIENTE DAÑADO O DESCONFIGURADO",
      "CODIGOUBICACIONDAÑO": 133,
      "DESCRIPCIONUBICACIONDAÑO": "CLIENTE"
    },
    {
      "CODIGOCAUSA": 9198,
      "DESCRIPCIONCAUSA": "Televisor desconfigurado",
      "CODIGOTIPODAÑO": 187576,
      "DESCRIPCIONTIPODAÑO": "TELEVISOR DEL CLIENTE DAÑADO O DESCONFIGURADO",
      "CODIGOUBICACIONDAÑO": 133,
      "DESCRIPCIONUBICACIONDAÑO": "CLIENTE"
    },
    {
      "CODIGOCAUSA": 7004,
      "DESCRIPCIONCAUSA": "Trasformador dañado",
      "CODIGOTIPODAÑO": 187715,
      "DESCRIPCIONTIPODAÑO": "TRANSFORMADOR DAÑADO",
      "CODIGOUBICACIONDAÑO": 106,
      "DESCRIPCIONUBICACIONDAÑO": "set to box"
    },
    {
      "CODIGOCAUSA": 8414,
      "DESCRIPCIONCAUSA": "NO ENCIENDE",
      "CODIGOTIPODAÑO": 187586,
      "DESCRIPCIONTIPODAÑO": "CAMBIO DE STB QUEMADO O DAÑADO",
      "CODIGOUBICACIONDAÑO": 106,
      "DESCRIPCIONUBICACIONDAÑO": "set to box"
    },
    {
      "CODIGOCAUSA": 8408,
      "DESCRIPCIONCAUSA": "EQUIPO ROBADO",
      "CODIGOTIPODAÑO": 187586,
      "DESCRIPCIONTIPODAÑO": "CAMBIO DE STB QUEMADO O DAÑADO",
      "CODIGOUBICACIONDAÑO": 106,
      "DESCRIPCIONUBICACIONDAÑO": "set to box"
    },
    {
      "CODIGOCAUSA": 8424,
      "DESCRIPCIONCAUSA": "SE REINICIA",
      "CODIGOTIPODAÑO": 187586,
      "DESCRIPCIONTIPODAÑO": "CAMBIO DE STB QUEMADO O DAÑADO",
      "CODIGOUBICACIONDAÑO": 106,
      "DESCRIPCIONUBICACIONDAÑO": "set to box"
    },
    {
      "CODIGOCAUSA": 8403,
      "DESCRIPCIONCAUSA": "CLIENTE DAÑO EL EQUIPO",
      "CODIGOTIPODAÑO": 187586,
      "DESCRIPCIONTIPODAÑO": "CAMBIO DE STB QUEMADO O DAÑADO",
      "CODIGOUBICACIONDAÑO": 133,
      "DESCRIPCIONUBICACIONDAÑO": "CLIENTE"
    },
    {
      "CODIGOCAUSA": 8404,
      "DESCRIPCIONCAUSA": "CLIENTE LO SOLICITA",
      "CODIGOTIPODAÑO": 187586,
      "DESCRIPCIONTIPODAÑO": "CAMBIO DE STB QUEMADO O DAÑADO",
      "CODIGOUBICACIONDAÑO": 106,
      "DESCRIPCIONUBICACIONDAÑO": "set to box"
    },
    {
      "CODIGOCAUSA": 8407,
      "DESCRIPCIONCAUSA": "ENTRADAS HDMI DAÑADAS",
      "CODIGOTIPODAÑO": 187586,
      "DESCRIPCIONTIPODAÑO": "CAMBIO DE STB QUEMADO O DAÑADO",
      "CODIGOUBICACIONDAÑO": 106,
      "DESCRIPCIONUBICACIONDAÑO": "set to box"
    },
    {
      "CODIGOCAUSA": 8419,
      "DESCRIPCIONCAUSA": "PLUG DE ALIMENTACION",
      "CODIGOTIPODAÑO": 187586,
      "DESCRIPCIONTIPODAÑO": "CAMBIO DE STB QUEMADO O DAÑADO",
      "CODIGOUBICACIONDAÑO": 106,
      "DESCRIPCIONUBICACIONDAÑO": "set to box"
    },
    {
      "CODIGOCAUSA": 8426,
      "DESCRIPCIONCAUSA": "TRASLADO Y EXTRAVIO",
      "CODIGOTIPODAÑO": 187586,
      "DESCRIPCIONTIPODAÑO": "CAMBIO DE STB QUEMADO O DAÑADO",
      "CODIGOUBICACIONDAÑO": 133,
      "DESCRIPCIONUBICACIONDAÑO": "CLIENTE"
    },
    {
      "CODIGOCAUSA": 8432,
      "DESCRIPCIONCAUSA": "RECEPTOR IR DAÑADO",
      "CODIGOTIPODAÑO": 187586,
      "DESCRIPCIONTIPODAÑO": "CAMBIO DE STB QUEMADO O DAÑADO",
      "CODIGOUBICACIONDAÑO": 106,
      "DESCRIPCIONUBICACIONDAÑO": "set to box"
    },
    {
      "CODIGOCAUSA": 9215,
      "DESCRIPCIONCAUSA": "Uso del Control Remoto",
      "CODIGOTIPODAÑO": 187600,
      "DESCRIPCIONTIPODAÑO": "CAMBIO DE CONTROL REMOTO DE STB",
      "CODIGOUBICACIONDAÑO": 133,
      "DESCRIPCIONUBICACIONDAÑO": "CLIENTE"
    },
    {
      "CODIGOCAUSA": 1102,
      "DESCRIPCIONCAUSA": "control remoto dañado",
      "CODIGOTIPODAÑO": 187600,
      "DESCRIPCIONTIPODAÑO": "CAMBIO DE CONTROL REMOTO DE STB",
      "CODIGOUBICACIONDAÑO": 106,
      "DESCRIPCIONUBICACIONDAÑO": "set to box"
    },
    {
      "CODIGOCAUSA": 1103,
      "DESCRIPCIONCAUSA": "HDMI dañado o en mal estado",
      "CODIGOTIPODAÑO": 187792,
      "DESCRIPCIONTIPODAÑO": "CAMBIO DE HDMI",
      "CODIGOUBICACIONDAÑO": 106,
      "DESCRIPCIONUBICACIONDAÑO": "set to box"
    },
    {
      "CODIGOCAUSA": 7016,
      "DESCRIPCIONCAUSA": "Cliente suspendido",
      "CODIGOTIPODAÑO": 187585,
      "DESCRIPCIONTIPODAÑO": "SUSPENDIDO",
      "CODIGOUBICACIONDAÑO": 133,
      "DESCRIPCIONUBICACIONDAÑO": "CLIENTE"
    },
    {
      "CODIGOCAUSA": 1063,
      "DESCRIPCIONCAUSA": "falla en central",
      "CODIGOTIPODAÑO": 187595,
      "DESCRIPCIONTIPODAÑO": "FALLA GENERAL",
      "CODIGOUBICACIONDAÑO": 118,
      "DESCRIPCIONUBICACIONDAÑO": "PLATAFORMA"
    },
    {
      "CODIGOCAUSA": 5527,
      "DESCRIPCIONCAUSA": "Aprovisionamiento de Servicios",
      "CODIGOTIPODAÑO": 187794,
      "DESCRIPCIONTIPODAÑO": "SERVICIO MAL APROVISIONADO",
      "CODIGOUBICACIONDAÑO": 118,
      "DESCRIPCIONUBICACIONDAÑO": "PLATAFORMA"
    },
    {
      "CODIGOCAUSA": 9203,
      "DESCRIPCIONCAUSA": "Problemas de Paquetes de STB",
      "CODIGOTIPODAÑO": 187588,
      "DESCRIPCIONTIPODAÑO": "PROBLEMA DE PAQUETES DE STB",
      "CODIGOUBICACIONDAÑO": 118,
      "DESCRIPCIONUBICACIONDAÑO": "PLATAFORMA"
    }
  ]